tap_bexio/__init__.py
tap_bexio/client.py
tap_bexio/schemas/projects.json
tap_bexio/streams.py
tap_bexio/tap.py
tap_bexio/tests/__init__.py
tap_bexio/tests/test_core.py
tap_bexio-0.0.1.dist-info/entry_points.txt
tap_bexio-0.0.1.dist-info/WHEEL
tap_bexio-0.0.1.dist-info/METADATA
tap_bexio-0.0.1.dist-info/RECORD
