Metadata-Version: 2.1
Name: tap-bexio
Version: 0.0.1
Summary: `tap-bexio` is a Singer tap for bexio, built with the Meltano SDK for Singer Taps.
License: Apache 2.0
Keywords: ELT,bexio
Author: Nino Müller
Requires-Python: >=3.6.2,<3.11
Classifier: License :: Other/Proprietary License
Classifier: Programming Language :: Python :: 3
Classifier: Programming Language :: Python :: 3.10
Classifier: Programming Language :: Python :: 3.7
Classifier: Programming Language :: Python :: 3.8
Classifier: Programming Language :: Python :: 3.9
Requires-Dist: requests (>=2.25.1,<3.0.0)
Requires-Dist: singer-sdk (>=0.3.17,<0.4.0)
